{
  "tasks": [
    {
      "title": "Improve the user experience of the Netflix app to make it easier for users to find and watch movies and TV shows.",
      "dueDate": "2023-12-08",
      "id": 8,
      "status": "Over Due"
    },
    {
      "title": "Design a new user interface for the Tesla infotainment system.",
      "dueDate": "2024-01-10",
      "status": "Assigned",
      "id": 9
    },
    {
      "title": "Create a more intuitive user interface for the Apple Watch.",
      "dueDate": "2024-01-19",
      "status": "Assigned",
      "id": 10
    }
  ],
  "members": [
    {
      "name": "Alice",
      "id": "1234"
    },
    {
      "name": "Bob",
      "id": "5678"
    },
    {
      "name": "Carol",
      "id": "9012"
    },
    {
      "name": "Dave",
      "id": "3456"
    },
    {
      "name": "Eve",
      "id": "7890"
    },
    {
      "name": "Frank",
      "id": "0123"
    },
    {
      "name": "Grace",
      "id": "4567"
    },
    {
      "name": "Henry",
      "id": "8901"
    },
    {
      "name": "Isaac",
      "id": "2345"
    },
    {
      "name": "Jessica",
      "id": "6789"
    },
    {
      "name": "Kevin",
      "id": "0012"
    },
    {
      "name": "Linda",
      "id": "4567"
    },
    {
      "name": "Michael",
      "id": "8901"
    },
    {
      "name": "Nancy",
      "id": "2345"
    },
    {
      "name": "Oliver",
      "id": "6789"
    }
  ],
  "teams": [
    {
      "taskId": "8",
      "name": "Team Brainstorming Brigade",
      "teamMembers": {
        "member1": "Grace",
        "member2": "Frank",
        "member3": "Eve",
        "member4": "Dave"
      },
      "id": 2
    }
  ]
}